geogif/__init__.py
geogif/cli.py
geogif/core.py
geogif/geoframe.py
realgeogif-0.1.1.dist-info/LICENSE
realgeogif-0.1.1.dist-info/METADATA
realgeogif-0.1.1.dist-info/WHEEL
realgeogif-0.1.1.dist-info/entry_points.txt
realgeogif-0.1.1.dist-info/top_level.txt
realgeogif-0.1.1.dist-info/RECORD
