Metadata-Version: 2.2
Name: realgeogif
Version: 0.1.1
Summary: Real GeoGIF: GeoTIFF cross-bred with GIF for spatiotemporal data visualization
Author-email: Casey Backes <casey.backes@gmail.com>
Maintainer-email: Casey Backes <casey.backes@gmail.com>
License: MIT
Project-URL: Homepage, https://github.com/caseybackes/geogif
Project-URL: Bug Tracker, https://github.com/caseybackes/geogif/issues
Project-URL: Documentation, https://geogif.readthedocs.io/
Project-URL: Source Code, https://github.com/caseybackes/geogif
Keywords: gis,geospatial,gif,geotiff,animation
Classifier: Development Status :: 3 - Alpha
Classifier: Intended Audience :: Science/Research
Classifier: Intended Audience :: Developers
Classifier: License :: OSI Approved :: MIT License
Classifier: Programming Language :: Python :: 3
Classifier: Programming Language :: Python :: 3.8
Classifier: Programming Language :: Python :: 3.9
Classifier: Programming Language :: Python :: 3.10
Classifier: Programming Language :: Python :: 3.11
Classifier: Topic :: Scientific/Engineering :: GIS
Classifier: Topic :: Multimedia :: Graphics
Requires-Python: >=3.8
License-File: LICENSE
Requires-Dist: numpy>=1.19.0
Requires-Dist: Pillow>=9.0.0
Requires-Dist: GDAL>=3.0.0
Provides-Extra: dev
Requires-Dist: pytest>=7.0.0; extra == "dev"
Requires-Dist: pytest-cov>=4.0.0; extra == "dev"
Requires-Dist: black>=23.0.0; extra == "dev"
Requires-Dist: isort>=5.0.0; extra == "dev"
Requires-Dist: flake8>=6.0.0; extra == "dev"
Requires-Dist: mypy>=1.0.0; extra == "dev"
Provides-Extra: docs
Requires-Dist: sphinx>=6.0.0; extra == "docs"
Requires-Dist: sphinx-rtd-theme>=1.0.0; extra == "docs"
